aiocaldav/__init__.py
aiocaldav/davclient.py
aiocaldav/objects.py
aiocaldav/elements/__init__.py
aiocaldav/elements/base.py
aiocaldav/elements/cdav.py
aiocaldav/elements/dav.py
aiocaldav/elements/ical.py
aiocaldav/lib/__init__.py
aiocaldav/lib/error.py
aiocaldav/lib/namespace.py
aiocaldav/lib/python_utilities.py
aiocaldav/lib/url.py
aiocaldav/lib/vcal.py
aiocaldav-0.5.1.dist-info/METADATA
aiocaldav-0.5.1.dist-info/RECORD
aiocaldav-0.5.1.dist-info/WHEEL
aiocaldav-0.5.1.dist-info/top_level.txt
