Metadata-Version: 2.1
Name: aiocaldav
Version: 0.5.1
Summary: asynchronous CalDAV (RFC4791) client library
Home-page: https://github.com/ThomasChiroux/aiocaldav
Author: Cyril Robert
Author-email: cyril@hippie.io
Maintainer: Thomas Chiroux
Maintainer-email: thomas@chroux.com
License: GPL
Platform: UNKNOWN
Classifier: Development Status :: 4 - Beta
Classifier: Intended Audience :: Developers
Classifier: License :: OSI Approved :: GNU General Public License (GPL)
Classifier: License :: OSI Approved :: Apache Software License
Classifier: Operating System :: OS Independent
Classifier: Programming Language :: Python
Classifier: Programming Language :: Python :: 3.6
Classifier: Topic :: Office/Business :: Scheduling
Classifier: Topic :: Software Development :: Libraries :: Python Modules
